yt_helper/__init__.py
yt_helper/legacy.py
yt_helper/scripts/__init__.py
yt_helper/scripts/download.py
yt_helper-0.2.11.dist-info/LICENSE.txt
yt_helper-0.2.11.dist-info/METADATA
yt_helper-0.2.11.dist-info/WHEEL
yt_helper-0.2.11.dist-info/entry_points.txt
yt_helper-0.2.11.dist-info/top_level.txt
yt_helper-0.2.11.dist-info/RECORD
