Metadata-Version: 2.1
Name: yt-helper
Version: 0.2.11
Summary: Light wrapper to youtube-dl with a simplified CLI for downloading media
Home-page: https://github.com/kenjyco/yt-helper
Author: Ken
Author-email: kenjyco@gmail.com
License: MIT
Download-URL: https://github.com/kenjyco/yt-helper/tarball/v0.2.11
Keywords: youtube-dl,youtube,ffmpeg,sox,rtmpdump,video,audio,cli,command-line,download,helper,kenjyco
Platform: UNKNOWN
Classifier: Development Status :: 3 - Alpha
Classifier: Environment :: Console
Classifier: Intended Audience :: Developers
Classifier: License :: OSI Approved :: MIT License
Classifier: Operating System :: MacOS :: MacOS X
Classifier: Operating System :: POSIX :: Linux
Classifier: Programming Language :: Python :: 3.5
Classifier: Programming Language :: Python
Classifier: Topic :: Software Development :: Libraries
Classifier: Topic :: Utilities
Requires-Dist: click
Requires-Dist: fs-helper
Requires-Dist: input-helper
Requires-Dist: youtube-dl
Provides-Extra: redis-helper
Requires-Dist: redis-helper ; extra == 'redis-helper'
